{"forge_marker": 1,

"defaults": {

"model": "forge:multi-layer",

"transform": "forge:default-block"},
"variants": {
"inventory0": [{"custom": { "base": "granite#normal", "Solid": "granite#normal", "Translucent": "wtfcore:base#moss" }}],
"inventory1": [{"custom": { "base": "granite#normal", "Solid": "granite#normal", "Translucent": "wtfcore:base#soul" }}],
"inventory2": [{"custom": { "base": "granite#normal", "Solid": "granite#normal", "Translucent": "wtfcore:base#cracked" }}],
"type" : {
"moss": {"custom": { "base": "granite#normal", "Solid": "granite#normal", "Translucent": "wtfcore:base#moss" }},
"soul": {"custom": { "base": "granite#normal", "Solid": "granite#normal", "Translucent": "wtfcore:base#soul" }},
"cracked": {"custom": { "base": "granite#normal", "Solid": "granite#normal", "Translucent": "wtfcore:base#cracked" }}
}
}
}
