{"forge_marker": 1,
"defaults": {
"model": "forge:multi-layer",
"transform": "forge:default-block"},
"variants": {
"inventory0": [{"custom": { "base": "andesite#normal", "Solid": "andesite#normal", "Translucent": "wtfcore:base#lava" }}],
"inventory1": [{"custom": { "base": "andesite#normal", "Solid": "andesite#normal" }}],
"inventory2": [{"custom": { "base": "andesite#normal", "Solid": "andesite#normal" }}],
"type" : {
"lava_crust": {"custom": { "base": "andesite#normal", "Solid": "andesite#normal", "Translucent": "wtfcore:base#lava" }},
"drip_water": {"custom": { "base": "andesite#normal", "Solid": "andesite#normal"}},
"drip_lava": {"custom": { "base": "andesite#normal", "Solid": "andesite#normal"}}
},
"fast" : {"true" : {},"false" : {}
}}}
